command_processor.sv


module command_processor (
    input  logic         clk,
    input  logic         reset_n,

    input  logic [31:0]  read_addr,
    input  logic [31:0]  read_size,
    output logic [7:0]   status,
    input  logic [7:0]   control,

    output logic [28:0]  avm_address,
    output logic         avm_read,
    output logic [7:0]   avm_burstcount,
    input  logic [63:0]  avm_readdata,
    input  logic         avm_readdatavalid,
    input  logic         avm_waitrequest,

    input  logic         rast_enable,
    output logic         rast_clear,
    output logic         vertex_valid,
    output logic [191:0] vertex_data
);
    
    enum logic [2:0] { IDLE, WAIT_REQ, READ_COMMAND, DO_CLEAR_COMMAND, DO_TRIANGLE_COMMAND } 
                  state, next_state;

    logic         busy, next_busy, size_error, next_size_error;
    logic [1:0]   vertices_remaining, next_vertices_remaining;

    logic [28:0]  next_address;
    logic         next_read;
    logic [7:0]   next_burst;

    logic         next_rast_clear;
    logic [191:0] next_vertex_data;
    logic         next_vertex_valid;

    wire start = control[0];

    always_ff @(posedge clk) begin
        if (!reset_n) begin
            busy            <= 1'b0;
            size_error      <= 1'b0;
            vertices_remaining <= 2'b00;
            
            avm_address     <= '0;
            avm_read        <= 1'b0;
            avm_burstcount  <= 8'h01;

            rast_clear      <= 1'b0;
            vertex_data     <= '0;
            vertex_valid    <= 1'b0;

            state           <= IDLE;
        end
        else begin
            busy            <= next_busy;
            size_error      <= next_size_error;
            vertices_remaining <= next_vertices_remaining;
            
            avm_address     <= next_address;
            avm_read        <= next_read;
            avm_burstcount  <= next_burst;

            rast_clear      <= next_rast_clear;
            vertex_data     <= next_vertex_data;
            vertex_valid    <= next_vertex_valid;

            state           <= next_state;
        end
    end
    
    always_comb begin
        
        next_busy      = busy;
        next_size_error = size_error;
        next_vertices_remaining = vertices_remaining;

        next_address   = avm_address;
        next_read      = avm_read;
        next_burst     = avm_burstcount;

        next_rast_clear = 1'b0;
        next_vertex_data = vertex_data;
        next_vertex_valid = 1'b0;

        next_state     = state;

        case (state)
            IDLE: begin
                next_busy = 1'b0;
                if (start) begin
                    next_busy = 1'b1;
                    next_size_error = 1'b0;

                    next_address    = read_addr[28:0];
                    next_read       = 1'b1;
                    next_burst      = (read_size < 8'd1) ? 8'd1 : (read_size + 8'h7) >> 3;

                    next_state      = WAIT_REQ;
                end
            end

            WAIT_REQ: begin
                if (!avm_waitrequest) begin
                    next_read  = 1'b0;
                    next_state = READ_COMMAND;
                end
            end

            READ_COMMAND: begin
                if (avm_readdatavalid) begin
                    case (avm_readdata[7:0])
                        8'h00: begin
                            next_state = IDLE;
                        end

                        8'h01: begin // Clear command
                            if (avm_burstcount != 8'h01) begin
                                next_size_error = 1'b1;
                                next_state = IDLE;
                            end
                            else begin
                                next_state = DO_CLEAR_COMMAND;
                            end
                        end

                        8'h02: begin // DRAW_PIXEL command (not implemented)
                            next_state = IDLE;
                        end

                        8'h03: begin // DRAW_TRIANGLE command
                            if (avm_burstcount != 8'h04) begin
                                next_size_error = 1'b1;
                                next_state = IDLE;
                            end
                            else begin
                                next_state = DO_TRIANGLE_COMMAND;
                                next_vertices_remaining = 2'd3;
                            end
                        end

                        default: begin
                            next_state = IDLE;
                        end
                    endcase
                end
            end

            DO_CLEAR_COMMAND: begin
                next_rast_clear = 1'b1;
                next_state = IDLE;
            end

            DO_TRIANGLE_COMMAND: begin
                if (vertices_remaining == 0) begin
                    next_vertex_valid = 1'b1;
                    next_state = IDLE;
                end
                else if (avm_readdatavalid) begin
                    next_vertices_remaining = vertices_remaining - 1;
                    next_vertex_data[(vertices_remaining-1)*64 +: 64] = avm_readdata;
                end
            end

            default: next_state = IDLE;

        endcase
    end

    assign status[0] = busy; // READY/BUSY
    assign status[1] = size_error; // SIZE_ERROR
    assign status[2] = vertex_valid; // VERTEX_VALID
    assign status[3] = (state == WAIT_REQ) & avm_waitrequest;  // stuck indicator
    assign status[4] = (vertex_data[7:0]   == 8'hAA);  // byte 0 of vertex 2
    assign status[5] = (vertex_data[71:64] == 8'hBB);  // byte 0 of vertex 1
    assign status[6] = (vertex_data[135:128] == 8'hCC); // byte 0 of vertex 0
    assign status[7] = (status[4] & status[5] & status[6]); // all correct

endmodule

command_processor.vcd
$version Generated by VerilatedVcd $end
$timescale 1ps $end
 $scope module TOP $end
  $var wire 1 6 clk $end
  $var wire 1 7 reset_n $end
  $var wire 32 8 read_addr [31:0] $end
  $var wire 32 9 read_size [31:0] $end
  $var wire 8 : status [7:0] $end
  $var wire 8 ; control [7:0] $end
  $var wire 29 < avm_address [28:0] $end
  $var wire 1 = avm_read $end
  $var wire 8 > avm_burstcount [7:0] $end
  $var wire 64 ? avm_readdata [63:0] $end
  $var wire 1 A avm_readdatavalid $end
  $var wire 1 B avm_waitrequest $end
  $var wire 1 C rast_enable $end
  $var wire 1 D rast_clear $end
  $var wire 1 E vertex_valid $end
  $var wire 192 F vertex_data [191:0] $end
  $scope module command_processor $end
   $var wire 1 6 clk $end
   $var wire 1 7 reset_n $end
   $var wire 32 8 read_addr [31:0] $end
   $var wire 32 9 read_size [31:0] $end
   $var wire 8 : status [7:0] $end
   $var wire 8 ; control [7:0] $end
   $var wire 29 < avm_address [28:0] $end
   $var wire 1 = avm_read $end
   $var wire 8 > avm_burstcount [7:0] $end
   $var wire 64 ? avm_readdata [63:0] $end
   $var wire 1 A avm_readdatavalid $end
   $var wire 1 B avm_waitrequest $end
   $var wire 1 C rast_enable $end
   $var wire 1 D rast_clear $end
   $var wire 1 E vertex_valid $end
   $var wire 192 F vertex_data [191:0] $end
   $var wire 3 0 state [2:0] $end
   $var wire 3 # next_state [2:0] $end
   $var wire 1 1 busy $end
   $var wire 1 $ next_busy $end
   $var wire 1 2 size_error $end
   $var wire 1 % next_size_error $end
   $var wire 2 3 vertices_remaining [1:0] $end
   $var wire 2 & next_vertices_remaining [1:0] $end
   $var wire 29 ' next_address [28:0] $end
   $var wire 1 ( next_read $end
   $var wire 8 ) next_burst [7:0] $end
   $var wire 1 4 next_rast_clear $end
   $var wire 192 * next_vertex_data [191:0] $end
   $var wire 1 5 next_vertex_valid $end
   $var wire 1 L start $end
  $upscope $end
 $upscope $end
$enddefinitions $end


#0
b000 #
0$
0%
b00 &
b00000000000000000000000000000 '
0(
b00000000 )
b000000000000000000000000000000000000000000000000000000000000000000000000000000000000000000000000000000000000000000000000000000000000000000000000000000000000000000000000000000000000000000000000 *
b000 0
01
02
b00 3
04
05
06
07
b00000000000000000000000000000000 8
b00000000000000000000000000000000 9
b00000000 :
b00000000 ;
b00000000000000000000000000000 <
0=
b00000000 >
b0000000000000000000000000000000000000000000000000000000000000000 ?
0A
1B
0C
0D
0E
b000000000000000000000000000000000000000000000000000000000000000000000000000000000000000000000000000000000000000000000000000000000000000000000000000000000000000000000000000000000000000000000000 F
0L
#1
b00000001 )
16
b00000001 >
#2
06
#3
16
#4
06
#5
16
#6
06
#7
16
#8
06
#9
16
#10
06
17
#11
16
#12
b001 #
1$
b00011000000000000000000000000 '
1(
b00000100 )
06
b00000011000000000000000000000000 8
b00000000000000000000000000100000 9
b00000001 ;
1L
#13
b001 0
11
16
b00001001 :
b00011000000000000000000000000 <
1=
b00000100 >
#14
06
b00000000 ;
0L
#15
16
#16
b010 #
0(
06
b00000001 :
0B
#17
b010 0
16
0=
#18
06
1B
#19
16
#20
b100 #
b11 &
06
b0000000000000000000000000000000000000000000000000000000000000011 ?
1A
#21
b10 &
b000000000000000000000000000000000000000000000000000000000000001100000000000000000000000000000000000000000000000000000000000000000000000000000000000000000000000000000000000000000000000000000000 *
b100 0
b11 3
16
#22
b11 &
b000000000000000000000000000000000000000000000000000000000000000000000000000000000000000000000000000000000000000000000000000000000000000000000000000000000000000000000000000000000000000000000000 *
06
0A
#23
16
#24
b10 &
b000100010001000100010001000100010001000100010001000100011100110000000000000000000000000000000000000000000000000000000000000000000000000000000000000000000000000000000000000000000000000000000000 *
06
b0001000100010001000100010001000100010001000100010001000111001100 ?
1A
#25
b01 &
b000100010001000100010001000100010001000100010001000100011100110000010001000100010001000100010001000100010001000100010001110011000000000000000000000000000000000000000000000000000000000000000000 *
b10 3
16
b01000001 :
b000100010001000100010001000100010001000100010001000100011100110000000000000000000000000000000000000000000000000000000000000000000000000000000000000000000000000000000000000000000000000000000000 F
#26
b000100010001000100010001000100010001000100010001000100011100110000100010001000100010001000100010001000100010001000100010101110110000000000000000000000000000000000000000000000000000000000000000 *
06
b0010001000100010001000100010001000100010001000100010001010111011 ?
#27
b00 &
b000100010001000100010001000100010001000100010001000100011100110000100010001000100010001000100010001000100010001000100010101110110010001000100010001000100010001000100010001000100010001010111011 *
b01 3
16
b01100001 :
b000100010001000100010001000100010001000100010001000100011100110000100010001000100010001000100010001000100010001000100010101110110000000000000000000000000000000000000000000000000000000000000000 F
#28
b000100010001000100010001000100010001000100010001000100011100110000100010001000100010001000100010001000100010001000100010101110110011001100110011001100110011001100110011001100110011001110101010 *
06
b0011001100110011001100110011001100110011001100110011001110101010 ?
#29
b000 #
b00 3
15
16
b11110001 :
b000100010001000100010001000100010001000100010001000100011100110000100010001000100010001000100010001000100010001000100010101110110011001100110011001100110011001100110011001100110011001110101010 F
#30
06
0A
#31
0$
b000 0
05
16
b11110101 :
1E
#32
06
#33
01
16
b11110000 :
0E
#34
06
07
b00000000000000000000000000000000 8
b00000000000000000000000000000000 9
b0000000000000000000000000000000000000000000000000000000000000000 ?
#35
b00000000000000000000000000000 '
b00000001 )
b000000000000000000000000000000000000000000000000000000000000000000000000000000000000000000000000000000000000000000000000000000000000000000000000000000000000000000000000000000000000000000000000 *
16
b00000000 :
b00000000000000000000000000000 <
b00000001 >
b000000000000000000000000000000000000000000000000000000000000000000000000000000000000000000000000000000000000000000000000000000000000000000000000000000000000000000000000000000000000000000000000 F
#36
06
#37
16
#38
06
#39
16
#40
06
#41
16
#42
06
#43
16
#44
06
17
#45
16
#46
b001 #
1$
b00011000000000000000000000000 '
1(
06
b00000011000000000000000000000000 8
b00000000000000000000000000001000 9
b00000001 ;
1L
#47
b001 0
11
16
b00001001 :
b00011000000000000000000000000 <
1=
#48
06
b00000000 ;
0L
#49
16
#50
b010 #
0(
06
b00000001 :
0B
#51
b010 0
16
0=
#52
06
1B
#53
16
#54
b011 #
06
b0000000000000000000000000000000000000000000000000000000000000001 ?
1A
#55
b000 #
b011 0
14
16
#56
06
0A
#57
0$
b000 0
04
16
1D
#58
06
#59
01
16
b00000000 :
0D
#60
06
07
b00000000000000000000000000000000 8
b00000000000000000000000000000000 9
b0000000000000000000000000000000000000000000000000000000000000000 ?
#61
b00000000000000000000000000000 '
16
b00000000000000000000000000000 <
#62
06
#63
16
#64
06
#65
16
#66
06
#67
16
#68
06
#69
16
#70
06
17
#71
16
#72
b001 #
1$
b00011000000000000000000000000 '
1(
06
b00000011000000000000000000000000 8
b00000000000000000000000000001000 9
b00000001 ;
1L
#73
b001 0
11
16
b00001001 :
b00011000000000000000000000000 <
1=
#74
06
b00000000 ;
0L
#75
16
#76
b010 #
0(
06
b00000001 :
0B
#77
b010 0
16
0=
#78
06
1B
#79
16
#80
b000 #
1%
06
b0000000000000000000000000000000000000000000000000000000000000011 ?
1A
#81
0$
b000 0
12
16
b00000011 :
#82
06
0A
#83
01
16
b00000010 :
#84
06
#85
16
#86
06
#87
16
#88
06
07
b00000000000000000000000000000000 8
b00000000000000000000000000000000 9
b0000000000000000000000000000000000000000000000000000000000000000 ?
#89
0%
b00000000000000000000000000000 '
02
16
b00000000 :
b00000000000000000000000000000 <
#90
06
#91
16
#92
06
#93
16
#94
06
#95
16
#96
06
#97
16
#98
06
17
#99
16
#100
b001 #
1$
b00011000000000000000000000000 '
1(
b00000100 )
06
b00000011000000000000000000000000 8
b00000000000000000000000000100000 9
b00000001 ;
1L
#101
b001 0
11
16
b00001001 :
b00011000000000000000000000000 <
1=
b00000100 >
#102
06
b00000000 ;
0L
#103
16
#104
b010 #
0(
06
b00000001 :
0B
#105
b010 0
16
0=
#106
06
1B
#107
16
#108
b000 #
1%
06
b0000000000000000000000000000000000000000000000000000000000000001 ?
1A
#109
0$
b000 0
12
16
b00000011 :
#110
06
0A
#111
01
16
b00000010 :
#112
06
#113
16
#114
06
#115
16
#116
06
07
b00000000000000000000000000000000 8
b00000000000000000000000000000000 9
b0000000000000000000000000000000000000000000000000000000000000000 ?
#117
0%
b00000000000000000000000000000 '
b00000001 )
02
16
b00000000 :
b00000000000000000000000000000 <
b00000001 >
#118
06
#119
16
#120
06
#121
16
#122
06
#123
16
#124
06
#125
16
#126
06
17
#127
16
#128
b001 #
1$
b00011000000000000000000000000 '
1(
06
b00000011000000000000000000000000 8
b00000000000000000000000000001000 9
b00000001 ;
1L
#129
b001 0
11
16
b00001001 :
b00011000000000000000000000000 <
1=
#130
06
b00000000 ;
0L
#131
16
#132
b010 #
0(
06
b00000001 :
0B
#133
b010 0
16
0=
#134
06
1B
#135
16
#136
b000 #
06
b0000000000000000000000000000000000000000000000000000000011111111 ?
1A
#137
0$
b000 0
16
#138
06
0A
#139
01
16
b00000000 :
#140
06
#141
16
#142
06
#143
16
#144
06
07
b00000000000000000000000000000000 8
b00000000000000000000000000000000 9
b0000000000000000000000000000000000000000000000000000000000000000 ?
#145
b00000000000000000000000000000 '
16
b00000000000000000000000000000 <
#146
06
#147
16
#148
06
#149
16
#150
06
#151
16
#152
06
#153
16
#154
06
17
#155
16
#156
b001 #
1$
b00011000000000000000000000000 '
1(
06
b00000011000000000000000000000000 8
b00000000000000000000000000001000 9
b00000001 ;
1L
#157
b001 0
11
16
b00001001 :
b00011000000000000000000000000 <
1=
#158
06
b00000000 ;
0L
#159
16
#160
b010 #
0(
06
b00000001 :
0B
#161
b010 0
16
0=
#162
06
1B
#163
16
#164
b000 #
1%
06
b0000000000000000000000000000000000000000000000000000000000000011 ?
1A
#165
0$
b000 0
12
16
b00000011 :
#166
06
0A
#167
01
16
b00000010 :
#168
06
#169
16
#170
06
#171
16
#172
b001 #
1$
0%
1(
b00000100 )
06
b00000000000000000000000000100000 9
b00000001 ;
1L
#173
b001 0
11
02
16
b00001001 :
1=
b00000100 >
#174
06
b00000000 ;
0L
#175
16
#176
b010 #
0(
06
b00000001 :
0B
#177
b010 0
16
0=
#178
06
1B
#179
16
#180
b100 #
b11 &
06
1A
#181
b10 &
b000000000000000000000000000000000000000000000000000000000000001100000000000000000000000000000000000000000000000000000000000000000000000000000000000000000000000000000000000000000000000000000000 *
b100 0
b11 3
16
#182
b11 &
b000000000000000000000000000000000000000000000000000000000000000000000000000000000000000000000000000000000000000000000000000000000000000000000000000000000000000000000000000000000000000000000000 *
06
0A
#183
16
#184
b10 &
b000100010001000100010001000100010001000100010001000100011100110000000000000000000000000000000000000000000000000000000000000000000000000000000000000000000000000000000000000000000000000000000000 *
06
b0001000100010001000100010001000100010001000100010001000111001100 ?
1A
#185
b01 &
b000100010001000100010001000100010001000100010001000100011100110000010001000100010001000100010001000100010001000100010001110011000000000000000000000000000000000000000000000000000000000000000000 *
b10 3
16
b01000001 :
b000100010001000100010001000100010001000100010001000100011100110000000000000000000000000000000000000000000000000000000000000000000000000000000000000000000000000000000000000000000000000000000000 F
#186
b000100010001000100010001000100010001000100010001000100011100110000100010001000100010001000100010001000100010001000100010101110110000000000000000000000000000000000000000000000000000000000000000 *
06
b0010001000100010001000100010001000100010001000100010001010111011 ?
#187
b00 &
b000100010001000100010001000100010001000100010001000100011100110000100010001000100010001000100010001000100010001000100010101110110010001000100010001000100010001000100010001000100010001010111011 *
b01 3
16
b01100001 :
b000100010001000100010001000100010001000100010001000100011100110000100010001000100010001000100010001000100010001000100010101110110000000000000000000000000000000000000000000000000000000000000000 F
#188
b000100010001000100010001000100010001000100010001000100011100110000100010001000100010001000100010001000100010001000100010101110110011001100110011001100110011001100110011001100110011001110101010 *
06
b0011001100110011001100110011001100110011001100110011001110101010 ?
#189
b000 #
b00 3
15
16
b11110001 :
b000100010001000100010001000100010001000100010001000100011100110000100010001000100010001000100010001000100010001000100010101110110011001100110011001100110011001100110011001100110011001110101010 F
#190
06
0A
#191
0$
b000 0
05
16
b11110101 :
1E
#192
06
#193
01
16
b11110000 :
0E
#194
06
07
b00000000000000000000000000000000 8
b00000000000000000000000000000000 9
b0000000000000000000000000000000000000000000000000000000000000000 ?
#195
b00000000000000000000000000000 '
b00000001 )
b000000000000000000000000000000000000000000000000000000000000000000000000000000000000000000000000000000000000000000000000000000000000000000000000000000000000000000000000000000000000000000000000 *
16
b00000000 :
b00000000000000000000000000000 <
b00000001 >
b000000000000000000000000000000000000000000000000000000000000000000000000000000000000000000000000000000000000000000000000000000000000000000000000000000000000000000000000000000000000000000000000 F
#196
06
#197
16
#198
06
#199
16
#200
06
#201
16
#202
06
#203
16
#204
06
17
#205
16
#206
b001 #
1$
b00011000000000000000000000000 '
1(
b00000100 )
06
b00000011000000000000000000000000 8
b00000000000000000000000000100000 9
b00000001 ;
1L
#207
b001 0
11
16
b00001001 :
b00011000000000000000000000000 <
1=
b00000100 >
#208
06
b00000000 ;
0L
#209
16
#210
b010 #
0(
06
b00000001 :
0B
#211
b010 0
16
0=
#212
06
1B
#213
16
#214
b100 #
b11 &
06
b0000000000000000000000000000000000000000000000000000000000000011 ?
1A
#215
b10 &
b000000000000000000000000000000000000000000000000000000000000001100000000000000000000000000000000000000000000000000000000000000000000000000000000000000000000000000000000000000000000000000000000 *
b100 0
b11 3
16
#216
b11 &
b000000000000000000000000000000000000000000000000000000000000000000000000000000000000000000000000000000000000000000000000000000000000000000000000000000000000000000000000000000000000000000000000 *
06
0A
#217
16
#218
06
#219
16
#220
06
#221
16
#222
06
#223
16
#224
06
#225
16
#226
06
#227
16
#228
06
#229
16
#230
06
#231
16
#232
b10 &
b101010101010101010101010101010101010101010101010101010101010101000000000000000000000000000000000000000000000000000000000000000000000000000000000000000000000000000000000000000000000000000000000 *
06
b1010101010101010101010101010101010101010101010101010101010101010 ?
1A
#233
b01 &
b101010101010101010101010101010101010101010101010101010101010101010101010101010101010101010101010101010101010101010101010101010100000000000000000000000000000000000000000000000000000000000000000 *
b10 3
16
b101010101010101010101010101010101010101010101010101010101010101000000000000000000000000000000000000000000000000000000000000000000000000000000000000000000000000000000000000000000000000000000000 F
#234
b10 &
b101010101010101010101010101010101010101010101010101010101010101000000000000000000000000000000000000000000000000000000000000000000000000000000000000000000000000000000000000000000000000000000000 *
06
0A
#235
16
#236
06
#237
16
#238
06
#239
16
#240
b01 &
b101010101010101010101010101010101010101010101010101010101010101010111011101110111011101110111011101110111011101110111011101110110000000000000000000000000000000000000000000000000000000000000000 *
06
b1011101110111011101110111011101110111011101110111011101110111011 ?
1A
#241
b00 &
b101010101010101010101010101010101010101010101010101010101010101010111011101110111011101110111011101110111011101110111011101110111011101110111011101110111011101110111011101110111011101110111011 *
b01 3
16
b00100001 :
b101010101010101010101010101010101010101010101010101010101010101010111011101110111011101110111011101110111011101110111011101110110000000000000000000000000000000000000000000000000000000000000000 F
#242
b01 &
b101010101010101010101010101010101010101010101010101010101010101010111011101110111011101110111011101110111011101110111011101110110000000000000000000000000000000000000000000000000000000000000000 *
06
0A
#243
16
#244
06
#245
16
#246
06
#247
16
#248
06
#249
16
#250
06
#251
16
#252
06
#253
16
#254
06
#255
16
#256
06
#257
16
#258
06
#259
16
#260
06
#261
16
#262
06
#263
16
#264
06
#265
16
#266
06
#267
16
#268
06
#269
16
#270
06
#271
16
#272
b00 &
b101010101010101010101010101010101010101010101010101010101010101010111011101110111011101110111011101110111011101110111011101110111100110011001100110011001100110011001100110011001100110011001100 *
06
b1100110011001100110011001100110011001100110011001100110011001100 ?
1A
#273
b000 #
b00 3
15
16
b101010101010101010101010101010101010101010101010101010101010101010111011101110111011101110111011101110111011101110111011101110111100110011001100110011001100110011001100110011001100110011001100 F
#274
06
0A
#275
0$
b000 0
05
16
b00100101 :
1E
#276
06
#277
01
16
b00100000 :
0E
#278
06
07
b00000000000000000000000000000000 8
b00000000000000000000000000000000 9
b0000000000000000000000000000000000000000000000000000000000000000 ?
#279
b00000000000000000000000000000 '
b00000001 )
b000000000000000000000000000000000000000000000000000000000000000000000000000000000000000000000000000000000000000000000000000000000000000000000000000000000000000000000000000000000000000000000000 *
16
b00000000 :
b00000000000000000000000000000 <
b00000001 >
b000000000000000000000000000000000000000000000000000000000000000000000000000000000000000000000000000000000000000000000000000000000000000000000000000000000000000000000000000000000000000000000000 F
#280
06
#281
16
#282
06
#283
16
#284
06
#285
16
#286
06
#287
16
#288
06
17
#289
16
#290
b001 #
1$
b00011000000000000000000000000 '
1(
b00000100 )
06
b00000011000000000000000000000000 8
b00000000000000000000000000100000 9
b00000001 ;
1L
#291
b001 0
11
16
b00001001 :
b00011000000000000000000000000 <
1=
b00000100 >
#292
06
b00000000 ;
0L
